heyflask/__init__.py
heyflask/heyflask.py
heyflask-0.2.0.dist-info/LICENSE
heyflask-0.2.0.dist-info/WHEEL
heyflask-0.2.0.dist-info/METADATA
heyflask-0.2.0.dist-info/RECORD
