Metadata-Version: 2.1
Name: heyflask
Version: 0.2.0
Summary: A Flask hello-world program.
Author: romk
Classifier: Development Status :: 4 - Beta
Classifier: Intended Audience :: Developers
Classifier: Programming Language :: Python
Classifier: Programming Language :: Python :: 3
Classifier: License :: OSI Approved :: MIT License
Classifier: Topic :: Internet :: WWW/HTTP
Classifier: Topic :: Software Development
Requires-Dist: Flask
Project-URL: Homepage, https://gitlab.com/romk/heyflask
